Slim_TPCA/Slim_TPCA.py
Slim_TPCA/__init__.py
Slim_TPCA-0.1.3.dist-info/LICENSE
Slim_TPCA-0.1.3.dist-info/METADATA
Slim_TPCA-0.1.3.dist-info/WHEEL
Slim_TPCA-0.1.3.dist-info/top_level.txt
Slim_TPCA-0.1.3.dist-info/RECORD
