Metadata-Version: 2.1
Name: Slim-TPCA
Version: 0.1.3
Summary: Slim-TPCA: a python package to expediate functional characterization of existing and newly identified protein complexes by optimizing existing TPCA algorithm implementations
Home-page: https://github.com/wangjun258/Slim_TPCA
Author: Siyuan Sun, Jun Wang
Author-email: Siyuan Sun <11930100@mail.sustech.edu.cn>
Project-URL: Homepage, https://github.com/pypa/Slim_TPCA
Project-URL: Bug Tracker, https://github.com/pypa/Slim_TPCA/issues
Classifier: Programming Language :: Python :: 3
Classifier: License :: OSI Approved :: MIT License
Classifier: Operating System :: OS Independent
Requires-Python: >=3.7
License-File: LICENSE
Requires-Dist: numpy (>=1.22.4)
Requires-Dist: pandas (>=1.4.3)
Requires-Dist: matplotlib (>=3.4.3)
Requires-Dist: scipy (>=1.7.1)
Requires-Dist: scikit-learn (>=1.2.2)
Requires-Dist: seaborn (>=0.11.2)
